Workbook

Sheet Model
B1: Zivvo — Unit Economics Model
B2: Australian rates · blue/yellow cells are inputs you can change · all else calculates automatically
B4: ASSUMPTIONS
B5: Standard price (before discount) | C5: 60 | D5: Venue's normal price for the slot
B6: Off-peak discount | C6: 0.2 | D6: Markdown the venue offers off-peak
B7: Venue commission rate | C7: 0.18 | D7: Zivvo's only revenue source; Groupon is 35–50%
B8: Stripe % fee (AU domestic card) | C8: 0.017 | D8: Stripe Connect standard AU rate
B9: Stripe fixed fee per transaction | C9: 0.3 | D9: Per-transaction flat component
B11: SINGLE BOOKING — WATERFALL
B12: Line item | C12: Amount | D12: Basis
B13: Standard price (before discount) | C13: =C5 -> 60 | D13: Venue's normal slot price
B14: Less: off-peak discount | C14: =-C5*C6 -> -12 | D14: Discount % × standard price
B15: Deal price shown in app = consumer pays | C15: =C5+C14 -> 48 | D15: What the customer is charged
B16: Venue commission | C16: =C15*C7 -> 8.64 | D16: Commission % × deal price
B17: Less: Stripe processing | C17: =-(C15*C8+C9) -> -1.116 | D17: % of deal price + fixed fee
B18: Net platform contribution | C18: =C16+C17 -> 7.524 | D18: Per booking, before overhead
B19: Venue receives | C19: =C15-C16 -> 39.36 | D19: Deal price less commission
B21: KEY OUTPUTS
B22: Net contribution per booking | C22: =C18 -> 7.524 | D22: The headline number
B23: Platform take as % of deal price | C23: =C18/C15 -> 0.15675 | D23: Effective net margin on the transaction
B24: Consumer saving vs standard price | C24: =-C14 -> 12 | D24: What the customer sees they saved

Sheet Break-even
B1: Zivvo — Break-even & Monthly View
B3: MONTHLY ASSUMPTIONS
B4: Net contribution per booking | C4: =Model!C18 -> 7.524 | D4: Pulled from Model sheet
B5: Avg bookings per venue per month | C5: 40 | D5: Conservative early estimate
B6: Number of live venues | C6: 15 | D6: Launch density target
B7: Monthly fixed costs | C7: 2500 | D7: Hosting, tooling, ops, subscriptions
B9: MONTHLY RESULT
B10: Total monthly bookings | C10: =C5*C6 -> 600
B11: Gross monthly contribution | C11: =C10*C4 -> 4514.4
B12: Net monthly profit (after fixed costs) | C12: =C11-C7 -> 2014.4
B14: BREAK-EVEN
B15: Bookings/month to break even | C15: =C7/C4 -> 332.27007 | D15: Fixed costs ÷ net contribution per booking
B16: Venues needed at this booking rate | C16: =(C7/C4)/C5 -> 8.3067517 | D16: Break-even bookings ÷ bookings per venue
B19: Note: change any yellow input on either sheet and every figure updates. All currency in A$ (AUD).

Sheet Scenarios
B1: Zivvo — Booking-Size Scenarios
B3: Compares net contribution across booking sizes. Deal price is the only input that changes; rates link to the Model sheet.
B5: Line item | C5: Single (A$20) | D5: Standard (A$48) | E5: Group (A$120)
B6: Deal price = consumer pays (input) | C6: 20 | D6: 48 | E6: 120
B7: Venue commission (18%) | C7: =C6*Model!$C$7 -> 3.6 | D7: =D6*Model!$C$7 -> 8.64 | E7: =E6*Model!$C$7 -> 21.6
B8: Less: Stripe processing | C8: =-(C6*Model!$C$8+Model!$C$9) -> -0.64 | D8: =-(D6*Model!$C$8+Model!$C$9) -> -1.116 | E8: =-(E6*Model!$C$8+Model!$C$9) -> -2.34
B9: Net platform contribution | C9: =C7+C8 -> 2.96 | D9: =D7+D8 -> 7.524 | E9: =E7+E8 -> 19.26
B10: Venue receives | C10: =C6-C7 -> 16.4 | D10: =D6-D7 -> 39.36 | E10: =E6-E7 -> 98.4
B12: Net take as % of deal price | C12: =C9/C6 -> 0.148 | D12: =D9/D6 -> 0.15675 | E12: =E9/E6 -> 0.1605
B14: Takeaway: net contribution scales with booking size — group/party bookings are the economically decisive segment.
